tau_ap/__init__.py
tau_ap/tau_ap.py
tau_ap-0.1.0.dist-info/licenses/LICENSE
tau_ap-0.1.0.dist-info/METADATA
tau_ap-0.1.0.dist-info/WHEEL
tau_ap-0.1.0.dist-info/top_level.txt
tau_ap-0.1.0.dist-info/RECORD
