Metadata-Version: 2.4
Name: tau_ap
Version: 0.1.0
Summary: Implementation of the Tau AP rank correlation measure
Author-email: Jack McKechnie <j.mckechnie.1@research.gla.ac.uk>
License: MIT
Requires-Python: >=3.7
License-File: LICENSE
Requires-Dist: numpy
Dynamic: license-file
